plumbersdk.py
plumber_python_sdk-0.0.2.dist-info/LICENSE
plumber_python_sdk-0.0.2.dist-info/METADATA
plumber_python_sdk-0.0.2.dist-info/WHEEL
plumber_python_sdk-0.0.2.dist-info/top_level.txt
plumber_python_sdk-0.0.2.dist-info/RECORD
